Workbook

Sheet Свод цен
A1: ГАЗЛИ–НУКУС 1 — СВОДНЫЙ ПЕРЕЧЕНЬ ЦЕН РЕСУРСОВ
A2: Строительство лупинга МГ «Газли–Нукус» I-нитка. Источник: локальные ресурсные сметы № 1-1 (Линейная часть), 1-2 (ЭХЗ), 1-3 (Внешнее электроснабжение 6 кВ средств УКЗ), 1-4 (АС). Цены в текущих ценах, сум. По каждому ресурсу — максимальная цена из 4 ЛРС.
A4: № | B4: Раздел | C4: Наименование ресурса | D4: Ед. изм. | E4: Цена за ед., сум (макс.) | F4: Цена мин., сум | G4: Кол-во разных цен | H4: Где встречается | I4: Примечание
A5: ЗАТРАТЫ ТРУДА
A6: 1 | B6: Затраты труда | C6: ДОП.ПЕРЕМЕЩЕНИЕ МАШИНИСТОВ ПО ТРАССЕ ДО МЕСТА РАБОТЫ | D6: ЧЕЛ.-Ч | G6: 0 | H6: 1-1, 1-2 | I6: оплата машинистов учтена в стоимости маш-ч
A7: 2 | B7: Затраты труда | C7: ДОП.ПЕРЕМЕЩЕНИЕ РАБОЧИХ-СТРОИТЕЛЕЙ ПО ТРАССЕ ДО МЕСТА РАБОТЫ | D7: ЧЕЛ.-Ч | E7: 25287.349 | F7: 25287.349 | G7: 1 | H7: 1-1, 1-2 | I7: цена из строки «Итого по трудовым ресурсам»
A8: 3 | B8: Затраты труда | C8: ЗАТРАТЫ ТРУДА МАШИНИСТОВ | D8: ЧЕЛ.-Ч | G8: 0 | H8: 1-1, 1-2, 1-3, 1-4 | I8: оплата машинистов учтена в стоимости маш-ч
A9: 4 | B9: Затраты труда | C9: ЗАТРАТЫ ТРУДА РАБОЧИХ МОНТАЖНИКОВ | D9: ЧЕЛ.-Ч | E9: 25287.349 | F9: 25287.349 | G9: 1 | H9: 1-2 | I9: цена из строки «Итого по трудовым ресурсам»
A10: 5 | B10: Затраты труда | C10: ЗАТРАТЫ ТРУДА РАБОЧИХ-СТРОИТЕЛЕЙ | D10: ЧЕЛ.-Ч | E10: 25287.349 | F10: 25287.349 | G10: 1 | H10: 1-1, 1-2, 1-3, 1-4 | I10: цена из строки «Итого по трудовым ресурсам»
A11: МАШИНЫ И МЕХАНИЗМЫ
A12: 6 | B12: Машины и механизмы | C12: АВТОГИДРОПОДЪЕМНИКИ ВЫСОТОЙ ПОДЪЕМА 12 М | D12: МАШ.-Ч | E12: 118630 | F12: 118630 | G12: 1 | H12: 1-2, 1-3
A13: 7 | B13: Машины и механизмы | C13: АВТОГРЕЙДЕР "КАМАЦУ" 149 КВТ (200 Л.С.) | D13: МАШ.-Ч | E13: 225000 | F13: 225000 | G13: 1 | H13: 1-2
A14: 8 | B14: Машины и механизмы | C14: АВТОГРЕЙДЕРЫ СРЕДНЕГО ТИПА 99 (135) КВТ (Л.С.) | D14: МАШ.-Ч | E14: 407372.3 | F14: 407372.3 | G14: 1 | H14: 1-1, 1-2, 1-4
A15: 9 | B15: Машины и механизмы | C15: АВТОКРАН МАРКИ ХZJ5556QZ100К ГРУЗОПОДЪЕМНОСТЬЮ 100 ТОНН | D15: МАШ.Ч | E15: 733894.48 | F15: 733894.48 | G15: 1 | H15: 1-4
A16: 10 | B16: Машины и механизмы | C16: АВТОМАТЫ СВАРОЧНЫЕ С НОМИНАЛЬНЫМ СВАРОЧНЫМ ТОКОМ 450-1250 А | D16: МАШ.-Ч | E16: 27770 | F16: 27770 | G16: 1 | H16: 1-2
A17: 11 | B17: Машины и механизмы | C17: АВТОМОБИЛИ БОРТОВЫЕ ГРУЗОПОДЪЕМНОСТЬЮ ДО 5 Т | D17: МАШ.-Ч | E17: 428434.3 | F17: 428434.3 | G17: 1 | H17: 1-1, 1-2, 1-3, 1-4
A18: 12 | B18: Машины и механизмы | C18: АВТОМОБИЛИ БОРТОВЫЕ ГРУЗОПОДЪЕМНОСТЬЮ ДО 8 Т | D18: МАШ.-Ч | E18: 495524.27 | F18: 495524.27 | G18: 1 | H18: 1-2, 1-3, 1-4
A19: 13 | B19: Машины и механизмы | C19: АВТОМОБИЛИ-САМОСВАЛЫ ГРУЗОПОДЪЕМНОСТЬЮ ДО 10 Т | D19: МАШ.-Ч | E19: 495524 | F19: 495524 | G19: 1 | H19: 1-1, 1-2, 1-4
A20: 14 | B20: Машины и механизмы | C20: АВТОМОБИЛИ-САМОСВАЛЫ ГРУЗОПОДЪЕМНОСТЬЮ ДО 7 Т | D20: МАШ.-Ч | E20: 140361 | F20: 140361 | G20: 1 | H20: 1-2, 1-4
A21: 15 | B21: Машины и механизмы | C21: АВТОПОГРУЗЧИКИ 5 Т | D21: МАШ.-Ч | E21: 143063 | F21: 143063 | G21: 1 | H21: 1-1, 1-2, 1-4
A22: 16 | B22: Машины и механизмы | C22: АВТОЦЕМЕНТОВОЗЫ 13 Т | D22: МАШ.-Ч | E22: 125710.66 | F22: 125710.66 | G22: 1 | H22: 1-2
A23: 17 | B23: Машины и механизмы | C23: АВТОЦИСТЕРНА, ОБЪЕМ ВОДЫ 8 М3 | D23: МАШ.-Ч | E23: 133766 | F23: 133766 | G23: 1 | H23: 1-2
... A33: 27 | B33: Машины и механизмы | C33: АППАРАТЫ ДЛЯ ГАЗОВОЙ СВАРКИ И РЕЗКИ | D33: МАШ.-Ч | E33: 23251 | F33: 23251 | G33: 1 | H33: 1-1, 1-2, 1-4
A34: 28 | B34: Машины и механизмы | C34: АППАРАТЫ ДРОБЕСТРУЙНЫЕ ПНЕВМАТИЧЕСКИЕ | D34: МАШ.-Ч | G34: 0 | H34: 1-1 | I34: цена в ЛРС не указана
A35: 29 | B35: Машины и механизмы | C35: АППАРАТЫ РЕНТГЕНО-ДЕФЕКТОСКОПИЧЕСКИЕ С ТОЛЩИНОЙ ПРОСВЕЧИВАЕМОЙ СТАЛИ ДО 25 ММ | D35: МАШ.-Ч | E35: 959.8 | F35: 959.8 | G35: 1 | H35: 1-1
A36: 30 | B36: Машины и механизмы | C36: БУЛЬДОЗЕР Т-140 МОЩНОСТЬЮ 102 (140) КВТ (Л.С.) | D36: МАШ.-Ч | E36: 141420.54 | F36: 141420.54 | G36: 1 | H36: 1-4
A37: 31 | B37: Машины и механизмы | C37: БУЛЬДОЗЕРЫ SНАNТUI SD32 МОЩНОСТЬЮ 235 (320) КВТ (Л.С.) | D37: МАШ.-Ч | E37: 665973.48 | F37: 665973.48 | G37: 1 | H37: 1-4
A38: 32 | B38: Машины и механизмы | C38: БУЛЬДОЗЕРЫ ПРИ РАБОТЕ НА ГИДРОЭНЕРГЕТИЧЕСКОМ СТРОИТЕЛЬСТВЕ И ГОРНОВСКРЫШНЫХ РАБОТАХ 79 (108) КВТ (Л.С.) | D38: МАШ.-Ч | E38: 628141.12 | F38: 628141.12 | G38: 1 | H38: 1-4
A39: 33 | B39: Машины и механизмы | C39: БУЛЬДОЗЕРЫ ПРИ РАБОТЕ НА ГИДРОЭНЕРГЕТИЧЕСКОМ СТРОИТЕЛЬСТВЕ И ГОРНОВСКРЫШНЫХ РАБОТАХ ДО 59 (80) КВТ (Л.С.) | D39: МАШ.-Ч | G39: 0 | H39: 1-4 | I39: цена в ЛРС не указана
A40: 34 | B40: Машины и механизмы | C40: БУЛЬДОЗЕРЫ ПРИ РАБОТЕ НА ДРУГИХ ВИДАХ СТРОИТЕЛЬСТВА (КРОМЕ ВОДОХОЗЯЙСТВЕННОГО) 132 (180) КВТ (Л.С.) | D40: МАШ.-Ч | E40: 665973.48 | F40: 665973.48 | G40: 1 | H40: 1-1
A41: 35 | B41: Машины и механизмы | C41: БУЛЬДОЗЕРЫ ПРИ РАБОТЕ НА ДРУГИХ ВИДАХ СТРОИТЕЛЬСТВА (КРОМЕ ВОДОХОЗЯЙСТВЕННОГО) 96 (130) КВТ (Л.С.) | D41: МАШ.-Ч | E41: 361374.45 | F41: 361374.45 | G41: 1 | H41: 1-2
A42: 36 | B42: Машины и механизмы | C42: БУЛЬДОЗЕРЫ ПРИ РАБОТЕ НА ДРУГИХ ВИДАХ СТРОИТЕЛЬСТВА 79 (108) КВТ (Л.С.) | D42: МАШ.-Ч | E42: 628141.12 | F42: 628141.12 | G42: 1 | H42: 1-1, 1-2, 1-4
A43: 37 | B43: Машины и механизмы | C43: БУЛЬДОЗЕРЫ ПРИ РАБОТЕ НА СООРУЖЕНИИ МАГИСТРАЛЬНЫХ ТРУБОПРОВОДОВ 121 (165) КВТ (Л.С.) | D43: МАШ.-Ч | E43: 665973.48 | F43: 665973.48 | G43: 1 | H43: 1-1
A44: 38 | B44: Машины и механизмы | C44: БУЛЬДОЗЕРЫ ПРИ РАБОТЕ НА СООРУЖЕНИИ МАГИСТРАЛЬНЫХ ТРУБОПРОВОДОВ 96 (130) КВТ (Л.С.) | D44: МАШ.-Ч | E44: 628141.12 | F44: 628141.12 | G44: 1 | H44: 1-1
A45: 39 | B45: Машины и механизмы | C45: БУЛЬДОЗЕРЫ ПРИ РАБОТЕ НА СООРУЖЕНИИ МАГИСТРАЛЬНЫХ ТРУБОПРОВОДОВ ДО 59 (80) КВТ (Л.С.) | D45: МАШ.-Ч | E45: 628141.12 | F45: 628141.12 | G45: 1 | H45: 1-1
A46: 40 | B46: Машины и механизмы | C46: БУНКЕРЫ | D46: МАШ.-Ч | E46: 3295.33 | F46: 3295.33 | G46: 1 | H46: 1-4
A47: 41 | B47: Машины и механизмы | C47: ВИБРАТОРЫ ГЛУБИННЫЕ | D47: МАШ.-Ч | E47: 67125 | F47: 67125 | G47: 1 | H47: 1-2, 1-4
A48: 42 | B48: Машины и механизмы | C48: ВИБРОПЛИТА СVР 110 | D48: МАШ.-Ч | E48: 125000 | F48: 125000 | G48: 1 | H48: 1-4
A49: 43 | B49: Машины и механизмы | C49: ВЫПРЯМИТЕЛИ СВАРОЧНЫЕ ЛИЕКОЛН ДС-400 | D49: МАШ.-Ч | E49: 330196 | F49: 330196 | G49: 1 | H49: 1-1
A50: 44 | B50: Машины и механизмы | C50: ВЫШКИ ТЕЛЕСКОПИЧЕСКИЕ 25 М | D50: МАШ.-Ч | E50: 142421 | F50: 142421 | G50: 1 | H50: 1-3
A51: 45 | B51: Машины и механизмы | C51: ГЛИНОМЕШАЛКИ 4 М3 | D51: МАШ.-Ч | E51: 25758 | F51: 25758 | G51: 1 | H51: 1-2
... A109: 103 | B109: Машины и механизмы | C109: ПЛЕТЕВОЗЫ НА АВТОМОБИЛЬНОМ ХОДУ 25 Т | D109: МАШ.-Ч | E109: 350000 | F109: 350000 | G109: 1 | H109: 1-1
A110: 104 | B110: Машины и механизмы | C110: ПЛЕТЕВОЗЫ НА АВТОМОБИЛЬНОМ ХОДУ ДО 12 Т | D110: МАШ.-Ч | G110: 0 | H110: 1-1 | I110: цена в ЛРС не указана
A111: 105 | B111: Машины и механизмы | C111: ПЛЕТЕВОЗЫ НА АВТОМОБИЛЬНОМ ХОДУ НА ШАССИ МАЗ ДО 30 Т | D111: МАШ.-Ч | E111: 415000 | F111: 415000 | G111: 1 | H111: 1-1
A112: 106 | B112: Машины и механизмы | C112: ПОГРУЗЧИКИ ОДНОКОВШОВЫЕ УНИВЕРСАЛЬНЫЕ ФРОНТАЛЬНЫЕ ПНЕВМОКОЛЕСНЫЕ 3 Т | D112: МАШ.-Ч | E112: 122000 | F112: 122000 | G112: 1 | H112: 1-1
A113: 107 | B113: Машины и механизмы | C113: ПОДВЕСКИ ТРОЛЛЕЙНЫЕ ГРУЗОПОДЪЕМНОСТЬЮ 35 Т С МЕТАЛЛИЧЕСКИМИ КАТКАМИ ДЛЯ ТРУБ ДИАМЕТРОМ 1020 ММ | D113: МАШ.-Ч | E113: 12575.213 | F113: 12575.213 | G113: 1 | H113: 1-1
A114: 108 | B114: Машины и механизмы | C114: ПОДВЕСКИ ТРОЛЛЕЙНЫЕ ГРУЗОПОДЪЕМНОСТЬЮ 63 Т С МЕТАЛЛИЧЕСКИМИ КАТКАМИ ДЛЯ ТРУБ ДИАМЕТРОМ 1020-1420 ММ | D114: МАШ.-Ч | E114: 18262.942 | F114: 18262.942 | G114: 1 | H114: 1-1
A115: 109 | B115: Машины и механизмы | C115: ПОДВЕСКИ ТРОЛЛЕЙНЫЕ С МЕТАЛЛИЧЕСКИМИ КАТКАМИ ДЛЯ ТРУБ ДИАМЕТРОМ 80-350 ММ | D115: МАШ.-Ч | E115: 12575.213 | F115: 12575.213 | G115: 1 | H115: 1-1
A116: 110 | B116: Машины и механизмы | C116: ПОДЪЕМНИКИ МАЧТОВЫЕ СТРОИТЕЛЬНЫЕ 0,5 Т | D116: МАШ.-Ч | E116: 27016 | F116: 27016 | G116: 1 | H116: 1-2, 1-4
A117: 111 | B117: Машины и механизмы | C117: ПОЛОТЕНЦЕ МЯГКОЕ ДЛЯ ТРУБ ДИАМЕТРОМ 1000 ММ | D117: МАШ.-Ч | E117: 25000 | F117: 25000 | G117: 1 | H117: 1-1
A118: 112 | B118: Машины и механизмы | C118: ПОЛОТЕНЦЕ МЯГКОЕ ДЛЯ ТРУБ ДИАМЕТРОМ 1200-1400 ММ | D118: МАШ.-Ч | E118: 25000 | F118: 25000 | G118: 1 | H118: 1-1
A119: 113 | B119: Машины и механизмы | C119: ПОЛУПРИЦЕПЫ ОБЩЕГО НАЗНАЧЕНИЯ 12 Т | D119: МАШ.-Ч | E119: 6912.1705 | F119: 6912.1705 | G119: 1 | H119: 1-4
A120: 114 | B120: Машины и механизмы | C120: ПРЕОБРАЗОВАТЕЛИ СВАРОЧНЫЕ С НОМИНАЛЬНЫМ СВАРОЧНЫМ ТОКОМ 315-500 А | D120: МАШ.-Ч | E120: 113572 | F120: 113572 | G120: 1 | H120: 1-1, 1-2, 1-4
A121: 115 | B121: Машины и механизмы | C121: ПРЕСС-НОЖНИЦЫ КОМБИНИРОВАННЫЕ | D121: МАШ.-Ч | E121: 15000 | F121: 15000 | G121: 1 | H121: 1-2, 1-4
A122: 116 | B122: Машины и механизмы | C122: ПРИЦЕПЫ ТРАКТОРНЫЕ 2 Т | D122: МАШ.-Ч | E122: 11303 | F122: 11303 | G122: 1 | H122: 1-1
... A127: 121 | B127: Машины и механизмы | C127: СТАНОК ДЛЯ РУБКИ АРМАТУРЫ | D127: МАШ.-Ч | E127: 75000 | F127: 75000 | G127: 1 | H127: 1-4
A128: 122 | B128: Машины и механизмы | C128: ТЕЛЕЖКИ ТРАКТОРНЫЕ 20 Т | D128: МАШ.-Ч | G128: 0 | H128: 1-1 | I128: цена в ЛРС не указана
A129: 123 | B129: Машины и механизмы | C129: ТРАКТОРЫ ЛЕСОХОЗЯЙСТВЕННЫЕ НА ГУСЕНИЧНОМ ХОДУ 58,8 (80) КВТ (Л.С.) | D129: МАШ.-Ч | E129: 345450.4 | F129: 345450.4 | G129: 1 | H129: 1-1
A130: 124 | B130: Машины и механизмы | C130: ТРАКТОРЫ НА ГУСЕНИЧНОМ ХОДУ 128,7 (175) КВТ (Л.С.) | D130: МАШ.-Ч | E130: 254507 | F130: 254507 | G130: 1 | H130: 1-1
A131: 125 | B131: Машины и механизмы | C131: ТРАКТОРЫ НА ГУСЕНИЧНОМ ХОДУ 132 (180) КВТ (Л.С.) | D131: МАШ.-Ч | E131: 345450.4 | F131: 345450.4 | G131: 1 | H131: 1-1
A132: 126 | B132: Машины и механизмы | C132: ТРАКТОРЫ НА ГУСЕНИЧНОМ ХОДУ 79 (108) КВТ (Л.С.) | D132: МАШ.-Ч | E132: 345450.4 | F132: 254507 | G132: 2 | H132: 1-1, 1-4 | I132: разные цены в ЛРС (2)
A133: 127 | B133: Машины и механизмы | C133: ТРАКТОРЫ НА ГУСЕНИЧНОМ ХОДУ ПРИ РАБОТЕ НА ДРУГИХ ВИДАХ СТРОИТЕЛЬСТВА (КРОМЕ ВОДОХОЗЯЙСТВЕННОГО) ДО 59 (80) КВТ (Л.С.) | D133: МАШ.-Ч | E133: 162412 | F133: 162412 | G133: 1 | H133: 1-1
A134: 128 | B134: Машины и механизмы | C134: ТРАКТОРЫ НА ГУСЕНИЧНОМ ХОДУ С ЛЕБЕДКОЙ 132 (180) КВТ (Л.С.) | D134: МАШ.-Ч | E134: 345450.4 | F134: 345450.4 | G134: 1 | H134: 1-1
A135: 129 | B135: Машины и механизмы | C135: ТРАКТОРЫ НА ПНЕВМОКОЛЕСНОМ ХОДУ ПРИ РАБОТЕ НА ДРУГИХ ВИДАХ СТРОИТЕЛЬСТВА (КРОМЕ ВОДОХОЗЯЙСТВЕННОГО) 59 (80) КВТ (Л.С.) | D135: МАШ.-Ч | E135: 155385 | F135: 155385 | G135: 1 | H135: 1-2, 1-3
A136: 130 | B136: Машины и механизмы | C136: ТРАМБОВКИ ПНЕВМАТИЧЕСКИЕ | D136: МАШ.-Ч | E136: 194485 | F136: 194485 | G136: 1 | H136: 1-1, 1-4
A137: 131 | B137: Машины и механизмы | C137: ТРУБОУКЛАДЧИК D-355С ГРУЗОПОДЪЕМНОСТЬЮ 92 Т | D137: МАШ.-Ч | E137: 644267.69 | F137: 644267.69 | G137: 1 | H137: 1-1
A138: 132 | B138: Машины и механизмы | C138: ТРУБОУКЛАДЧИКИ ДЛЯ ТРУБ ДИАМЕТРОМ ДО 400 ММ, ГРУЗОПОДЪЕМНОСТЬ 6,3 Т | D138: МАШ.-Ч | E138: 207624 | F138: 207624 | G138: 1 | H138: 1-1
A139: 133 | B139: Машины и механизмы | C139: ТЯГАЧИ СЕДЕЛЬНЫЕ 15 Т | D139: МАШ.-Ч | E139: 87051.382 | F139: 87051.382 | G139: 1 | H139: 1-4
A140: 134 | B140: Машины и механизмы | C140: УСТАНОВКИ ГОРИЗОНТАЛЬНОГО БУРЕНИЯ ДЛЯ ТРУБ ДИАМЕТРОМ 1220-1420 ММ | D140: МАШ.-Ч | E140: 4149283.6 | F140: 4149283.6 | G140: 1 | H140: 1-1
A141: 135 | B141: Машины и механизмы | C141: УСТАНОВКИ ГОРИЗОНТАЛЬНОГО БУРЕНИЯ ДЛЯ ТРУБ ДИАМЕТРОМ 325-630 ММ | D141: МАШ.-Ч | E141: 4149283.6 | F141: 4149283.6 | G141: 1 | H141: 1-1
A142: 136 | B142: Машины и механизмы | C142: УСТАНОВКИ ДЛЯ ГИДРАВЛИЧЕСКИХ ИСПЫТАНИЙ ТРУБОПРОВОДОВ, ДАВЛЕНИЕ НАГНЕТАНИЯ НИЗКОЕ 0,1 (1) МПА (КГС/СМ2), ВЫСОКОЕ 10 (100) МПА (КГС/СМ2) ПРИ РАБОТЕ ОТ ПЕРЕДВИЖНЫХ ЭЛЕКТРОСТАНЦИЙ | D142: МАШ.-Ч | E142: 175000 | F142: 175000 | G142: 1 | H142: 1-1
A143: 137 | B143: Машины и механизмы | C143: УСТАНОВКИ ДЛЯ ОТКРЫТОГО ВОДООТЛИВА НА БАЗЕ ТРАКТОРА 700 М3/ЧАС | D143: МАШ.-Ч | E143: 280602.72 | F143: 280602.72 | G143: 1 | H143: 1-1
A144: 138 | B144: Машины и механизмы | C144: УСТАНОВКИ ДЛЯ ПОДОГРЕВА СТЫКОВ | D144: МАШ.-Ч | E144: 3000 | F144: 3000 | G144: 1 | H144: 1-1
... A152: 146 | B152: Машины и механизмы | C152: ЦИСТЕРНЫ ПРИЦЕПНЫЕ 5 М3 | D152: МАШ.-Ч | E152: 3500 | F152: 3500 | G152: 1 | H152: 1-4
A153: 147 | B153: Машины и механизмы | C153: ЭКСКАВАТОР ОДНОКОВШОВЫЙ НА ГУСЕНИЧНОМ ХОДУ "САТЕRРILLАR-320D" ЕМКОСТЬЮ КОВША 1 М3 | D153: МАШ.-Ч | G153: 0 | H153: 1-4 | I153: цена в ЛРС не указана
A154: 148 | B154: Машины и механизмы | C154: ЭКСКАВАТОРЫ ОДНОКОВШОВЫЕ ДИЗЕЛЬНЫЕ НА ГУСЕНИЧНОМ ХОДУ ПРИ РАБОТЕ НА ДРУГИХ ВИДАХ СТРОИТЕЛЬСТВА (КРОМЕ ВОДОХОЗЯЙСТВЕННОГО) 0,4 М3 | D154: МАШ.-Ч | E154: 201233 | F154: 201233 | G154: 1 | H154: 1-2
A155: 149 | B155: Машины и механизмы | C155: ЭКСКАВАТОРЫ ОДНОКОВШОВЫЕ ДИЗЕЛЬНЫЕ НА ГУСЕНИЧНОМ ХОДУ ПРИ РАБОТЕ НА ДРУГИХ ВИДАХ СТРОИТЕЛЬСТВА (КРОМЕ ВОДОХОЗЯЙСТВЕННОГО) 0,5 М3 | D155: МАШ.-Ч | E155: 604049.1 | F155: 604049.1 | G155: 1 | H155: 1-1, 1-4
A156: 150 | B156: Машины и механизмы | C156: ЭКСКАВАТОРЫ ОДНОКОВШОВЫЕ ДИЗЕЛЬНЫЕ НА ГУСЕНИЧНОМ ХОДУ ПРИ РАБОТЕ НА ДРУГИХ ВИДАХ СТРОИТЕЛЬСТВА (КРОМЕ ВОДОХОЗЯЙСТВЕННОГО) 0,65 М3 | D156: МАШ.-Ч | G156: 0 | H156: 1-4 | I156: цена в ЛРС не указана
A157: 151 | B157: Машины и механизмы | C157: ЭКСКАВАТОРЫ ОДНОКОВШОВЫЕ ДИЗЕЛЬНЫЕ НА ГУСЕНИЧНОМ ХОДУ ПРИ РАБОТЕ НА ДРУГИХ ВИДАХ СТРОИТЕЛЬСТВА (КРОМЕ ВОДОХОЗЯЙСТВЕННОГО) 1 М3 | D157: МАШ.-Ч | E157: 336530 | F157: 336530 | G157: 1 | H157: 1-2, 1-4
A158: 152 | B158: Машины и механизмы | C158: ЭКСКАВАТОРЫ ОДНОКОВШОВЫЕ ДИЗЕЛЬНЫЕ НА ГУСЕНИЧНОМ ХОДУ ПРИ РАБОТЕ НА СООРУЖЕНИИ МАГИСТРАЛЬНЫХ ТРУБОПРОВОДОВ 0,25 М3 | D158: МАШ.-Ч | E158: 382204.96 | F158: 382204.96 | G158: 1 | H158: 1-1
A159: 153 | B159: Машины и механизмы | C159: ЭКСКАВАТОРЫ ОДНОКОВШОВЫЕ ДИЗЕЛЬНЫЕ НА ГУСЕНИЧНОМ ХОДУ ПРИ РАБОТЕ НА СООРУЖЕНИИ МАГИСТРАЛЬНЫХ ТРУБОПРОВОДОВ 0,65 М3 | D159: МАШ.-Ч | E159: 681807.21 | F159: 681807.21 | G159: 1 | H159: 1-1
A160: 154 | B160: Машины и механизмы | C160: ЭКСКАВАТОРЫ ОДНОКОВШОВЫЕ ДИЗЕЛЬНЫЕ НА ГУСЕНИЧНОМ ХОДУ ПРИ РАБОТЕ НА СООРУЖЕНИИ МАГИСТРАЛЬНЫХ ТРУБОПРОВОДОВ 1 М3 | D160: МАШ.-Ч | E160: 681807.21 | F160: 681807.21 | G160: 1 | H160: 1-1
A161: 155 | B161: Машины и механизмы | C161: ЭКСКАВАТОРЫ ОДНОКОВШОВЫЕ ДИЗЕЛЬНЫЕ НА ПНЕВМОКОЛЕСНОМ ХОДУ ПРИ РАБОТЕ НА ДРУГИХ ВИДАХ СТРОИТЕЛЬСТВА (КРОМЕ ВОДОХОЗЯЙСТВЕННОГО) 0,25 М3 | D161: МАШ.-Ч | E161: 162268 | F161: 162268 | G161: 1 | H161: 1-2, 1-4
A162: 156 | B162: Машины и механизмы | C162: ЭЛЕКТРОСТАНЦИИ ПЕРЕДВИЖНЫЕ 4 КВТ | D162: МАШ.-Ч | E162: 53495 | F162: 53495 | G162: 1 | H162: 1-1, 1-2
A163: 157 | B163: Машины и механизмы | C163: ЭЛЕКТРОСТАНЦИИ ПЕРЕДВИЖНЫЕ 60 КВТ | D163: МАШ.-Ч | E163: 467212.6 | F163: 467212.6 | G163: 1 | H163: 1-1
A164: 158 | B164: Машины и механизмы | C164: ЭЛЕКТРОСТАНЦИИ ПЕРЕДВИЖНЫЕ 75 КВТ | D164: МАШ.-Ч | E164: 456905.21 | F164: 456905.21 | G164: 1 | H164: 1-1
A165: МАТЕРИАЛЫ ПО НОРМАМ
A166: 159 | B166: Материалы по нормам | C166: АЦЕТИЛЕН ГАЗООБРАЗНЫЙ ТЕХНИЧЕСКИЙ | D166: М3 | E166: 11500 | F166: 11500 | G166: 1 | H166: 1-1, 1-4
A167: 160 | B167: Материалы по нормам | C167: АЦЕТИЛЕН РАСТВОРЕННЫЙ ТЕХНИЧЕСКИЙ МАРКИ А | D167: Т | E167: 12000000 | F167: 12000000 | G167: 1 | H167: 1-2
A168: 161 | B168: Материалы по нормам | C168: АЦЕТОН ТЕХНИЧЕСКИЙ СОРТ I | D168: Т | E168: 12000000 | F168: 12000000 | G168: 1 | H168: 1-2
A169: 162 | B169: Материалы по нормам | C169: БЕНЗИН АВИАЦИОННЫЙ Б-70 | D169: Т | E169: 17623900 | F169: 17623900 | G169: 1 | H169: 1-2
A170: 163 | B170: Материалы по нормам | C170: БЕНЗИН АВТОМОБИЛЬНЫЙ АИ-98, АИ-95 "ЭКСТРА", АИ-93 | D170: Т | E170: 10500000 | F170: 10500000 | G170: 1 | H170: 1-1
A171: 164 | B171: Материалы по нормам | C171: БЕНЗИН РАСТВОРИТЕЛЬ | D171: Т | E171: 10500000 | F171: 10500000 | G171: 1 | H171: 1-2, 1-3
A172: 165 | B172: Материалы по нормам | C172: БЕТОН М-150 | D172: М3 | E172: 639101 | F172: 639101 | G172: 1 | H172: 1-2
A173: 166 | B173: Материалы по нормам | C173: БЕТОН ТЯЖЕЛЫЙ КЛАССА В15 /М-200/ ФРАКЦИИ 5-20 ММ | D173: М3 | E173: 750000 | F173: 750000 | G173: 1 | H173: 1-2
A174: 167 | B174: Материалы по нормам | C174: БЕТОН ТЯЖЕЛЫЙ, КЛАСС В 27,5 (М350) | D174: М3 | E174: 950000 | F174: 950000 | G174: 1 | H174: 1-1
A175: 168 | B175: Материалы по нормам | C175: БИРКИ МАРКИРОВОЧНЫЕ | D175: 100ШТ | E175: 35357.143 | F175: 35357.143 | G175: 1 | H175: 1-2
A176: 169 | B176: Материалы по нормам | C176: БИРКИ МАРКИРОВОЧНЫЕ ДЛЯ КАБЕЛЕЙ | D176: 100ШТ | E176: 35357.143 | F176: 35357.143 | G176: 1 | H176: 1-2
A177: 170 | B177: Материалы по нормам | C177: БИТУМ | D177: Т | E177: 8500000 | F177: 8500000 | G177: 1 | H177: 1-2
... A187: 180 | B187: Материалы по нормам | C187: ВИНТЫ С ПОЛУКРУГЛОЙ ГОЛОВКОЙ ДЛИНОЙ 50 ММ | D187: Т | E187: 22500000 | F187: 22500000 | G187: 1 | H187: 1-3
...

Sheet Все ресурсы
A1: ГАЗЛИ–НУКУС 1 — ВСЕ РЕСУРСЫ ПО ЛРС
A2: Строительство лупинга МГ «Газли–Нукус» I-нитка. Источник: локальные ресурсные сметы № 1-1 (Линейная часть), 1-2 (ЭХЗ), 1-3 (Внешнее электроснабжение 6 кВ средств УКЗ), 1-4 (АС). Цены в текущих ценах, сум.
A4: ЛРС | B4: Часть | C4: Раздел | D4: № в ЛРС | E4: Наименование ресурса | F4: Ед. изм. | G4: Количество | H4: Цена за ед., сум | I4: Сумма, сум | J4: Стр. в исходном файле | K4: Примечание
A5: ЛРС № 1-1 | B5: Линейная часть | C5: Затраты труда | D5: 1 | E5: ЗАТРАТЫ ТРУДА РАБОЧИХ-СТРОИТЕЛЕЙ | F5: ЧЕЛ.-Ч | G5: 72164.73 | H5: 25287.349 | J5: 19 | K5: цена из строки «Итого по трудовым ресурсам»
A6: ЛРС № 1-1 | B6: Линейная часть | C6: Затраты труда | D6: 2 | E6: ЗАТРАТЫ ТРУДА МАШИНИСТОВ | F6: ЧЕЛ.-Ч | G6: 54806.818 | J6: 20 | K6: оплата машинистов учтена в стоимости маш-ч
A7: ЛРС № 1-1 | B7: Линейная часть | C7: Затраты труда | D7: 3 | E7: ДОП.ПЕРЕМЕЩЕНИЕ РАБОЧИХ-СТРОИТЕЛЕЙ ПО ТРАССЕ ДО МЕСТА РАБОТЫ | F7: ЧЕЛ.-Ч | G7: 5487.5097 | H7: 25287.349 | J7: 21 | K7: цена из строки «Итого по трудовым ресурсам»
A8: ЛРС № 1-1 | B8: Линейная часть | C8: Затраты труда | D8: 4 | E8: ДОП.ПЕРЕМЕЩЕНИЕ МАШИНИСТОВ ПО ТРАССЕ ДО МЕСТА РАБОТЫ | F8: ЧЕЛ.-Ч | G8: 5248.2777 | J8: 22 | K8: оплата машинистов учтена в стоимости маш-ч
A9: ЛРС № 1-1 | B9: Линейная часть | C9: Машины и механизмы | D9: 1 | E9: АВТОГРЕЙДЕРЫ СРЕДНЕГО ТИПА 99 (135) КВТ (Л.С.) | F9: МАШ.-Ч | G9: 0.4416 | H9: 407372.3 | I9: 179895.61 | J9: 26
A10: ЛРС № 1-1 | B10: Линейная часть | C10: Машины и механизмы | D10: 2 | E10: АВТОПОГРУЗЧИКИ 5 Т | F10: МАШ.-Ч | G10: 81.5208 | H10: 143063 | I10: 11662610 | J10: 27
A11: ЛРС № 1-1 | B11: Линейная часть | C11: Машины и механизмы | D11: 3 | E11: АГРЕГАТЫ СВАРОЧНЫЕ ДВУХПОСТОВЫЕ ДЛЯ РУЧНОЙ СВАРКИ НА ТРАКТОРЕ 79 КВТ (108 Л.С.) | F11: МАШ.-Ч | G11: 1728.1651 | H11: 456905.21 | I11: 7.8960765e+08 | J11: 28
A12: ЛРС № 1-1 | B12: Линейная часть | C12: Машины и механизмы | D12: 4 | E12: АГРЕГАТЫ СВАРОЧНЫЕ ПЕРЕДВИЖНЫЕ С НОМИНАЛЬНЫМ СВАРОЧНЫМ ТОКОМ 250-400 А С ДИЗЕЛЬНЫМ ДВИГАТЕЛЕМ | F12: МАШ.-Ч | G12: 25.7607 | H12: 111320 | I12: 2867681.1 | J12: 29
A13: ЛРС № 1-1 | B13: Линейная часть | C13: Машины и механизмы | D13: 5 | E13: АППАРАТЫ РЕНТГЕНО-ДЕФЕКТОСКОПИЧЕСКИЕ С ТОЛЩИНОЙ ПРОСВЕЧИВАЕМОЙ СТАЛИ ДО 25 ММ | F13: МАШ.-Ч | G13: 1267.7 | H13: 959.8 | I13: 1216738.5 | J13: 30
A14: ЛРС № 1-1 | B14: Линейная часть | C14: Машины и механизмы | D14: 6 | E14: АВТОМОБИЛИ-САМОСВАЛЫ ГРУЗОПОДЪЕМНОСТЬЮ ДО 10 Т | F14: МАШ.-Ч | G14: 74.1015 | H14: 495524 | I14: 36719072 | J14: 31
A15: ЛРС № 1-1 | B15: Линейная часть | C15: Машины и механизмы | D15: 7 | E15: БУЛЬДОЗЕРЫ ПРИ РАБОТЕ НА ДРУГИХ ВИДАХ СТРОИТЕЛЬСТВА 79 (108) КВТ (Л.С.) | F15: МАШ.-Ч | G15: 59.5094 | H15: 628141.12 | I15: 37380301 | J15: 32
A16: ЛРС № 1-1 | B16: Линейная часть | C16: Машины и механизмы | D16: 8 | E16: БУЛЬДОЗЕРЫ ПРИ РАБОТЕ НА ДРУГИХ ВИДАХ СТРОИТЕЛЬСТВА (КРОМЕ ВОДОХОЗЯЙСТВЕННОГО) 132 (180) КВТ (Л.С.) | F16: МАШ.-Ч | G16: 4.94 | H16: 665973.48 | I16: 3289909 | J16: 33
A17: ЛРС № 1-1 | B17: Линейная часть | C17: Машины и механизмы | D17: 9 | E17: БУЛЬДОЗЕРЫ ПРИ РАБОТЕ НА СООРУЖЕНИИ МАГИСТРАЛЬНЫХ ТРУБОПРОВОДОВ ДО 59 (80) КВТ (Л.С.) | F17: МАШ.-Ч | G17: 1.523 | H17: 628141.12 | I17: 956658.93 | J17: 34
A18: ЛРС № 1-1 | B18: Линейная часть | C18: Машины и механизмы | D18: 10 | E18: БУЛЬДОЗЕРЫ ПРИ РАБОТЕ НА СООРУЖЕНИИ МАГИСТРАЛЬНЫХ ТРУБОПРОВОДОВ 121 (165) КВТ (Л.С.) | F18: МАШ.-Ч | G18: 972.8656 | H18: 665973.48 | I18: 6.4790269e+08 | J18: 35
A19: ЛРС № 1-1 | B19: Линейная часть | C19: Машины и механизмы | D19: 11 | E19: БУЛЬДОЗЕРЫ ПРИ РАБОТЕ НА СООРУЖЕНИИ МАГИСТРАЛЬНЫХ ТРУБОПРОВОДОВ 96 (130) КВТ (Л.С.) | F19: МАШ.-Ч | G19: 491.57264 | H19: 628141.12 | I19: 3.0877699e+08 | J19: 36
A20: ЛРС № 1-1 | B20: Линейная часть | C20: Машины и механизмы | D20: 12 | E20: ГОРЕЛКИ ГАЗОПЛАМЕННЫЕ | F20: МАШ.-Ч | G20: 2300.911 | H20: 25000 | I20: 57522775 | J20: 37
... A155: ЛРС № 1-1 | B155: Линейная часть | C155: Материалы по нормам | D155: 66 | E155: ТРУБЫ СТАЛЬНЫЕ БЕСШОВНЫЕ, ГОРЯЧЕДЕФОРМИРОВАННЫЕ СО СНЯТОЙ ФАСКОЙ ИЗ СТАЛИ МАРОК 15, 20, 25 НАРУЖНЫЙ ДИАМЕТР 325 ММ ТОЛЩИНА СТЕНКИ 8 ММ | F155: М | G155: 187.86 | H155: 800000 | I155: 150288000 | J155: 175
A156: ЛРС № 1-1 | B156: Линейная часть | C156: Материалы по нормам | D156: 67 | E156: ТРУБЫ СТАЛЬНЫЕ ЭЛЕКТРОСВАРНЫЕ КЛАССА ПРОЧНОСТИ К 52 НАРУЖНЫЙ ДИАМЕТР 1020 ММ ТОЛЩИНА СТЕНОК 14,0 ММ | F156: М | G156: 3 | I156: 0 | J156: 176
A157: ЛРС № 1-1 | B157: Линейная часть | C157: Материалы по нормам | D157: 68 | E157: ТРУБЫ СТАЛЬНЫЕ ЭЛЕКТРОСВАРНЫЕ КЛАССА ПРОЧНОСТИ К 52 НАРУЖНЫЙ ДИАМЕТР 1020 ММ ТОЛЩИНА СТЕНОК 14,9 ММ | F157: М | G157: 1.82 | I157: 0 | J157: 177
A158: ЛРС № 1-1 | B158: Линейная часть | C158: Материалы по нормам | D158: 69 | E158: ЗНАКИ ОПОЗНАВАТЕЛЬНЫЕ МЕТАЛЛИЧЕСКИЕ | F158: ШТ | G158: 13.2 | H158: 1200000 | I158: 15840000 | J158: 178
A159: ЛРС № 1-1 | B159: Линейная часть | C159: Материалы по нормам | D159: 71 | E159: ПОРШЕНЬ ОЧИСТИТЕЛЬНЫЙ | F159: ШТ | G159: 0.32439 | H159: 50000 | I159: 16219.5 | J159: 179
A160: ЛРС № 1-1 | B160: Линейная часть | C160: Материалы по нормам | D160: 72 | E160: ПЛИТЫ ФУНДАМЕНТНЫЕ ИЗ БЕТОНА МАРКИ 200, АРМАТУРА 31 КГ/М3, ОБЪЕМОМ 0.2 М3 | F160: М3 | G160: 0.45 | H160: 950000 | I160: 427500 | J160: 180
A161: ЛРС № 1-1 | B161: Линейная часть | C161: Материалы по нормам | D161: 73 | E161: ПЛИТЫ СБОРНЫЕ ЖЕЛЕЗОБЕТОННЫЕ | F161: ШТ | G161: 34.419 | H161: 12000 | I161: 413028 | J161: 181
A162: ЛРС № 1-1 | B162: Линейная часть | C162: Материалы по нормам | D162: 74 | E162: УЗЛЫ ТРУБОПРОВОДОВ ИЗ ТРУБ ДИАМЕТРОМ 45Х4,5 ММ | F162: Т | G162: 0.03 | H162: 23500000 | I162: 705000 | J162: 182
A163: ЛРС № 1-1 | B163: Линейная часть | C163: Материалы по нормам | D163: 75 | E163: УЗЛЫ ТРУБОПРОВОДОВ ИЗ ТРУБ ДИАМЕТРОМ 108Х6 ММ | F163: Т | G163: 0.954 | H163: 23500000 | I163: 22419000 | J163: 183
A164: ЛРС № 1-1 | B164: Линейная часть | C164: Материалы по нормам | D164: 76 | E164: УЗЛЫ ТРУБОПРОВОДОВ ИЗ ТРУБ ДИАМЕТРОМ 325Х10 ММ | F164: Т | G164: 3.924 | H164: 23500000 | I164: 92214000 | J164: 184
A165: ЛРС № 1-1 | B165: Линейная часть | C165: Материалы по нормам | D165: 77 | E165: УЗЛЫ ТРУБОПРОВОДОВ ИЗ ТРУБ ДИАМЕТРОМ 377Х10 ММ | F165: Т | G165: 5.67 | H165: 23500000 | I165: 133245000 | J165: 185
A166: ЛРС № 1-1 | B166: Линейная часть | C166: Материалы по нормам | D166: 78 | E166: КОЛОНКА СВЕЧИ ИЗ ТРУБ ДИАМЕТРОМ 100 ММ | F166: ШТ | G166: 3 | H166: 5200000 | I166: 15600000 | J166: 186
A167: ЛРС № 1-1 | B167: Линейная часть | C167: Материалы по нормам | D167: 79 | E167: ВЕТОШЬ | F167: КГ | G167: 35.664 | H167: 5000 | I167: 178320 | J167: 187
A168: ЛРС № 1-1 | B168: Линейная часть | C168: Материалы по нормам | D168: 80 | E168: ПЕСОК МЕТАЛЛИЧЕСКИЙ | F168: Т | G168: 128.112 | H168: 0 | I168: 0 | J168: 188
A169: ЛРС № 1-1 | B169: Линейная часть | C169: Материалы по нормам | D169: 82 | E169: ПРОПАН-БУТАН, СМЕСЬ ТЕХНИЧЕСКАЯ | F169: КГ | G169: 5191.9596 | H169: 6904.761 | I169: 35849240 | J169: 189
... A179: ЛРС № 1-1 | B179: Линейная часть | C179: Материалы по нормам | D179: 92 | E179: ОТВОДЫ 90 ГРАД. С РАДИУСОМ КРИВИЗНЫ R 1,5ДУ НА РУ МЕНЕЕ ИЛИ 10 МПА (100 КГС/СМ2), ДИАМЕТРОМ УСЛОВНОГО ПРОХОДА 100 ММ, НАРУЖНЫМ ДИАМЕТРОМ 108 ММ, ТОЛЩИНОЙ СТЕНКИ, ММ: 6 | F179: ШТ | G179: 0 | H179: 0 | I179: 0 | J179: 199
A180: ЛРС № 1-1 | B180: Линейная часть | C180: Материалы по нормам | D180: 93 | E180: ОТВОДЫ КРУТОИЗОГНУТЫЕ ШТАМПОВАННЫЕ И ПРОТЯЖНЫЕ НА РУ МЕНЕЕ ИЛИ 10 МПА (100 КГ/СМ2) ИЗ ТРУБ СТАЛЬНЫХ БЕСШОВНЫХ ГОРЯЧЕДЕФОРМИРОВАННЫХ ИЛИ ХОЛОДНОДЕФОРМИРОВАННЫХ ИЗ СТАЛИ 20 ГНУТЫЕ ПОД УГЛОМ 90Ш С РАДИУСОМ КРИВИЗНЫ R 1.5ДУ, ДИАМЕТРОМ УСЛОВНОГО ПРОХОДА 300 ММ, НАРУЖНЫМ ДИАМЕТРОМ 325 ММ, ТОЛЩИНОЙ СТЕНКИ, ММ: 8 | F180: ШТ | G180: 5.4 | I180: 0 | J180: 200
A181: ЛРС № 1-1 | B181: Линейная часть | C181: Материалы по нормам | D181: 94 | E181: ТРОЙНИКИ ШТАМПОВАННЫЕ ИЗ УГЛЕРОДИСТОЙ СТАЛИ НА РУ ДО 16 МПА (160 КГС/СМ2) ИЗ ТРУБ СТАЛЬНЫХ БЕСШОВНЫХ ГОРЯЧЕДЕФОРМИРОВАННЫХ И ХОЛОДНОДЕФОРМИРОВАННЫХ ИЗ СТАЛИ 20 РАВНОПРОХОДНЫЕ, ДИАМЕТРОМ УСЛОВНОГО ПРОХОДА 100 ММ, НАРУЖНЫМ ДИАМЕТРОМ 108 ММ, ТОЛЩИНОЙ СТЕНКИ, ММ: 6 | F181: ШТ | G181: 1.8 | I181: 0 | J181: 201
A182: ЛРС № 1-1 | B182: Линейная часть | C182: Материалы по нормам | D182: 95 | E182: ТРОЙНИКИ ШТАМПОВАННЫЕ ИЗ УГЛЕРОДИСТОЙ СТАЛИ НА РУ ДО 16 МПА (160 КГС/СМ2) ИЗ ТРУБ СТАЛЬНЫХ БЕСШОВНЫХ ГОРЯЧЕДЕФОРМИРОВАННЫХ И ХОЛОДНОДЕФОРМИРОВАННЫХ ИЗ СТАЛИ 20 РАВНОПРОХОДНЫЕ, ДИАМЕТРОМ УСЛОВНОГО ПРОХОДА 300 ММ, НАРУЖНЫМ ДИАМЕТРОМ 325 ММ, ТОЛЩИНОЙ СТЕНКИ, ММ: 8 | F182: ШТ | G182: 4.2 | I182: 0 | J182: 202
A183: ЛРС № 1-1 | B183: Линейная часть | C183: Материалы по нормам | D183: 96 | E183: УЗЛЫ ТРУБОПРОВОДОВ С УСТАНОВКОЙ НЕОБХОДИМЫХ ДЕТАЛЕЙ (ФЛАНЦЕВ, ОТВОДОВ, ТРОЙНИКОВ, ПЕРЕХОДОВ, ЗАГЛУШЕК, ПАТРУБКОВ, П-ОБРАЗНЫХ КОМПЕНСАТОРОВ И Т.П.), ВХОДЯЩИХ В КОНСТРУКЦИЮ ТРУБОПРОВОДА, СО СБОРКОЙ НА ПОСТОЯННЫХ ПРОКЛАДКАХ, КРЕПЛЕНИЕМ БОЛТАМИ И СВАРКОЙ ИЗ ЭЛЕКТРОСВАРНЫХ ТРУБ БОЛЬШОГО ДИАМЕТРА СТ3СП-СТ6СП ДИАМЕТРОМ УСЛОВНОГО ПРОХОДА 1000 ММ, НАРУЖНЫМ ДИАМЕТРОМ 1020 ММ, ТОЛЩИНОЙ СТЕНКИ, ММ: 14 | F183: Т | G183: 12.6752 | I183: 0 | J183: 203
A184: ЛРС № 1-1 | B184: Линейная часть | C184: Материалы по нормам | D184: 97 | E184: КАНАТ ДВОЙНОЙ СВИВКИ, ТИПА ТЛК-О, КОНСТРУКЦИИ 6Х37(1+6+155)+1 О.С. БЕЗ ПОКРЫТИЯ, ИЗ ПРОВОЛОК МАРКИ В, МАРКИРОВОЧНАЯ ГРУППА 1770 Н/ММ2, ДИАМЕТРОМ, ММ: 13,5 | F184: 10М | G184: 9.17 | H184: 1200 | I184: 11004 | J184: 204
A185: ЛРС № 1-1 | B185: Линейная часть | C185: Материалы по нормам | D185: 98 | E185: КАНАТ ДВОЙНОЙ СВИВКИ, ТИПА ТЛК-О, КОНСТРУКЦИИ 6Х37(1+6+155)+1 О.С. БЕЗ ПОКРЫТИЯ, ИЗ ПРОВОЛОК МАРКИ В, МАРКИРОВОЧНАЯ ГРУППА 1770 Н/ММ2, ДИАМЕТРОМ, ММ: 33 | F185: 10М | G185: 36 | H185: 1200 | I185: 43200 | J185: 205
A186: ЛРС № 1-1 | B186: Линейная часть | C186: Ресурсы по проекту | D186: 1 | E186: АРМАТУРА Д6ММ АI | F186: КГ | G186: 3.28 | H186: 12000 | I186: 39360 | J186: 209
A187: ЛРС № 1-1 | B187: Линейная часть | C187: Ресурсы по проекту | D187: 2 | E187: ТРУБА 1-1020Х14-К60 С АКП ГОСТ 31447-2012 | F187: ПМ | G187: 363 | H187: 6250000 | I187: 2268750000 | J187: 210
A188: ЛРС № 1-1 | B188: Линейная часть | C188: Ресурсы по проекту | D188: 3 | E188: ТШС 1020Х(15)-325(10)-5,5-0,75-К52 | F188: ШТ | G188: 4 | H188: 45000000 | I188: 180000000 | J188: 211
A189: ЛРС № 1-1 | B189: Линейная часть | C189: Ресурсы по проекту | D189: 4 | E189: ТРОЙНИК 325Х10ММ К52 | F189: ШТ | G189: 2 | H189: 4500000 | I189: 9000000 | J189: 212
A190: ЛРС № 1-1 | B190: Линейная часть | C190: Ресурсы по проекту | D190: 5 | E190: ОТВОД 325Х10ММ К52 | F190: ШТ | G190: 10 | H190: 22350000 | I190: 223500000 | J190: 213
A191: ЛРС № 1-1 | B191: Линейная часть | C191: Ресурсы по проекту | D191: 6 | E191: ТШС 1020Х(15)-325Х(10)-5,5-0,75-К52 | F191: ШТ | G191: 1 | H191: 45000000 | I191: 45000000 | J191: 214
A192: ЛРС № 1-1 | B192: Линейная часть | C192: Ресурсы по проекту | D192: 7 | E192: ОТВОД 90ГР 325Х12ММ К52 | F192: ШТ | G192: 4 | H192: 3500000 | I192: 14000000 | J192: 215
A193: ЛРС № 1-1 | B193: Линейная часть | C193: Ресурсы по проекту | D193: 8 | E193: ТРУБА 22Х3ММ ГОСТ8732-75 | F193: ПМ | G193: 2 | H193: 45000 | I193: 90000 | J193: 216
A194: ЛРС № 1-1 | B194: Линейная часть | C194: Ресурсы по проекту | D194: 9 | E194: ТРУБА 60Х8ММ ГОСТ8732-78 | F194: ПМ | G194: 6 | H194: 65000 | I194: 390000 | J194: 217
A195: ЛРС № 1-1 | B195: Линейная часть | C195: Ресурсы по проекту | D195: 10 | E195: ТРУБА 325Х8ММ ГОСТ8732-78 | F195: ПМ | G195: 74 | H195: 800000 | I195: 59200000 | J195: 218
... A243: ЛРС № 1-1 | B243: Линейная часть | C243: Оборудование | D243: 3 | E243: КРАН ПРОХОДНОЙ ДУ300ММ, РУ8,0 МПА 11С723БК | F243: ШТ | G243: 3 | H243: 1.4116071e+08 | I243: 4.2348214e+08 | J243: 269
A244: ЛРС № 1-2 | B244: ЭХЗ | C244: Затраты труда | D244: 1 | E244: ЗАТРАТЫ ТРУДА РАБОЧИХ-СТРОИТЕЛЕЙ | F244: ЧЕЛ.-Ч | G244: 1309.8738 | H244: 25287.349 | J244: 19 | K244: цена из строки «Итого по трудовым ресурсам»
A245: ЛРС № 1-2 | B245: ЭХЗ | C245: Затраты труда | D245: 2 | E245: ЗАТРАТЫ ТРУДА МАШИНИСТОВ | F245: ЧЕЛ.-Ч | G245: 387.88744 | J245: 20 | K245: оплата машинистов учтена в стоимости маш-ч
A246: ЛРС № 1-2 | B246: ЭХЗ | C246: Затраты труда | D246: 3 | E246: ЗАТРАТЫ ТРУДА РАБОЧИХ МОНТАЖНИКОВ | F246: ЧЕЛ.-Ч | G246: 200.8 | H246: 25287.349 | J246: 21 | K246: цена из строки «Итого по трудовым ресурсам»
A247: ЛРС № 1-2 | B247: ЭХЗ | C247: Затраты труда | D247: 4 | E247: ДОП.ПЕРЕМЕЩЕНИЕ РАБОЧИХ-СТРОИТЕЛЕЙ ПО ТРАССЕ ДО МЕСТА РАБОТЫ | F247: ЧЕЛ.-Ч | G247: 20.64 | H247: 25287.349 | J247: 22 | K247: цена из строки «Итого по трудовым ресурсам»
A248: ЛРС № 1-2 | B248: ЭХЗ | C248: Затраты труда | D248: 5 | E248: ДОП.ПЕРЕМЕЩЕНИЕ МАШИНИСТОВ ПО ТРАССЕ ДО МЕСТА РАБОТЫ | F248: ЧЕЛ.-Ч | G248: 15.28 | J248: 23 | K248: оплата машинистов учтена в стоимости маш-ч
A249: ЛРС № 1-2 | B249: ЭХЗ | C249: Машины и механизмы | D249: 1 | E249: АВТОГИДРОПОДЪЕМНИКИ ВЫСОТОЙ ПОДЪЕМА 12 М | F249: МАШ.-Ч | G249: 1.3368 | H249: 118630 | I249: 158584.58 | J249: 27
A250: ЛРС № 1-2 | B250: ЭХЗ | C250: Машины и механизмы | D250: 2 | E250: АВТОГРЕЙДЕРЫ СРЕДНЕГО ТИПА 99 (135) КВТ (Л.С.) | F250: МАШ.-Ч | G250: 0.1275 | H250: 407372.3 | I250: 51939.968 | J250: 28
A251: ЛРС № 1-2 | B251: ЭХЗ | C251: Машины и механизмы | D251: 3 | E251: АВТОМАТЫ СВАРОЧНЫЕ С НОМИНАЛЬНЫМ СВАРОЧНЫМ ТОКОМ 450-1250 А | F251: МАШ.-Ч | G251: 0.6076 | H251: 27770 | I251: 16873.052 | J251: 29
A252: ЛРС № 1-2 | B252: ЭХЗ | C252: Машины и механизмы | D252: 4 | E252: АВТОПОГРУЗЧИКИ 5 Т | F252: МАШ.-Ч | G252: 0.90320482 | H252: 143063 | I252: 129215.19 | J252: 30
A253: ЛРС № 1-2 | B253: ЭХЗ | C253: Машины и механизмы | D253: 5 | E253: АВТОЦЕМЕНТОВОЗЫ 13 Т | F253: МАШ.-Ч | G253: 0.1133 | H253: 125710.66 | I253: 14243.017 | J253: 31
A254: ЛРС № 1-2 | B254: ЭХЗ | C254: Машины и механизмы | D254: 6 | E254: АГРЕГАТЫ СВАРОЧНЫЕ ДВУХПОСТОВЫЕ ДЛЯ РУЧНОЙ СВАРКИ НА АВТОМОБИЛЬНОМ ПРИЦЕПЕ | F254: МАШ.-Ч | G254: 6.7 | H254: 116872.46 | I254: 783045.48 | J254: 32
A255: ЛРС № 1-2 | B255: ЭХЗ | C255: Машины и механизмы | D255: 7 | E255: АГРЕГАТЫ СВАРОЧНЫЕ ПЕРЕДВИЖНЫЕ С НОМИНАЛЬНЫМ СВАРОЧНЫМ ТОКОМ 250-400 А С ДИЗЕЛЬНЫМ ДВИГАТЕЛЕМ | F255: МАШ.-Ч | G255: 26.0501 | H255: 111320 | I255: 2899897.1 | J255: 33
A256: ЛРС № 1-2 | B256: ЭХЗ | C256: Машины и механизмы | D256: 8 | E256: АВТОМОБИЛИ-САМОСВАЛЫ ГРУЗОПОДЪЕМНОСТЬЮ ДО 7 Т | F256: МАШ.-Ч | G256: 6.16 | H256: 140361 | I256: 864623.76 | J256: 34
A257: ЛРС № 1-2 | B257: ЭХЗ | C257: Машины и механизмы | D257: 9 | E257: АВТОМОБИЛИ-САМОСВАЛЫ ГРУЗОПОДЪЕМНОСТЬЮ ДО 10 Т | F257: МАШ.-Ч | G257: 0.17211373 | H257: 495524 | I257: 85286.484 | J257: 35
A258: ЛРС № 1-2 | B258: ЭХЗ | C258: Машины и механизмы | D258: 10 | E258: БУЛЬДОЗЕРЫ ПРИ РАБОТЕ НА ДРУГИХ ВИДАХ СТРОИТЕЛЬСТВА 79 (108) КВТ (Л.С.) | F258: МАШ.-Ч | G258: 2.829296 | H258: 628141.12 | I258: 1777197.2 | J258: 36
A259: ЛРС № 1-2 | B259: ЭХЗ | C259: Машины и механизмы | D259: 11 | E259: БУЛЬДОЗЕРЫ ПРИ РАБОТЕ НА ДРУГИХ ВИДАХ СТРОИТЕЛЬСТВА (КРОМЕ ВОДОХОЗЯЙСТВЕННОГО) 96 (130) КВТ (Л.С.) | F259: МАШ.-Ч | G259: 0.10638 | H259: 361374.45 | I259: 38443.014 | J259: 37
A260: ЛРС № 1-2 | B260: ЭХЗ | C260: Машины и механизмы | D260: 12 | E260: ВИБРАТОРЫ ГЛУБИННЫЕ | F260: МАШ.-Ч | G260: 0.374008 | H260: 67125 | I260: 25105.287 | J260: 38
... A331: ЛРС № 1-2 | B331: ЭХЗ | C331: Материалы по нормам | D331: 26 | E331: ЛАК БИТУМНЫЙ БТ-123 | F331: Т | G331: 0.0044111 | H331: 26000000 | I331: 114688.6 | J331: 112
A332: ЛРС № 1-2 | B332: ЭХЗ | C332: Материалы по нормам | D332: 27 | E332: ГРУНТОВКА ГФ-021 КРАСНО-КОРИЧНЕВАЯ | F332: Т | G332: 4.34e-06 | I332: 0 | J332: 113
A333: ЛРС № 1-2 | B333: ЭХЗ | C333: Материалы по нормам | D333: 28 | E333: ГРУНТОВКА БИТУМНАЯ | F333: Т | G333: 0.005311 | H333: 18482000 | I333: 98157.902 | J333: 114
A334: ЛРС № 1-2 | B334: ЭХЗ | C334: Материалы по нормам | D334: 29 | E334: БЕНЗИН РАСТВОРИТЕЛЬ | F334: Т | G334: 1.44e-05 | H334: 10500000 | I334: 151.2 | J334: 115
A335: ЛРС № 1-2 | B335: ЭХЗ | C335: Материалы по нормам | D335: 30 | E335: РАСТВОРИТЕЛЬ МАРКИ Р-4 | F335: Т | G335: 8.4e-06 | H335: 32411000 | I335: 272.2524 | J335: 116
A336: ЛРС № 1-2 | B336: ЭХЗ | C336: Материалы по нормам | D336: 31 | E336: ОЛИФА НАТУРАЛЬНАЯ | F336: КГ | G336: 1.7088 | H336: 19000 | I336: 32467.2 | J336: 117
A337: ЛРС № 1-2 | B337: ЭХЗ | C337: Материалы по нормам | D337: 32 | E337: ПАРАФИН НЕФТЯНОЙ ТВЕРДЫЙ П-3 | F337: Т | G337: 6e-05 | H337: 6032000 | I337: 361.92 | J337: 118
A338: ЛРС № 1-2 | B338: ЭХЗ | C338: Материалы по нормам | D338: 33 | E338: КЛЕЙ БМК-5К | F338: КГ | G338: 0.0386 | H338: 15000 | I338: 579 | J338: 119
A339: ЛРС № 1-2 | B339: ЭХЗ | C339: Материалы по нормам | D339: 34 | E339: ХОЛСТ СТЕКЛЯННЫЙ ВВГ | F339: 10М2 | G339: 0.038924 | H339: 80000 | I339: 3113.92 | J339: 120
A340: ЛРС № 1-2 | B340: ЭХЗ | C340: Материалы по нормам | D340: 35 | E340: МАСТИКА БИТУМНАЯ КРОВЕЛЬНАЯ ГОРЯЧАЯ | F340: Т | G340: 0.00285968 | H340: 8929000 | I340: 25534.083 | J340: 121
A341: ЛРС № 1-2 | B341: ЭХЗ | C341: Материалы по нормам | D341: 36 | E341: МАСТИКА КЛЕЯЩАЯ МОРОЗОСТОЙКАЯ БИТУМНО-МАСЛЯНАЯ МБ-50 | F341: Т | G341: 0.008 | H341: 8929000 | I341: 71432 | J341: 122
A342: ЛРС № 1-2 | B342: ЭХЗ | C342: Материалы по нормам | D342: 37 | E342: МАСТИКА ПО ПРОЕКТУ | F342: Т | G342: 0.001406 | H342: 10500000 | I342: 14763 | J342: 123
A343: ЛРС № 1-2 | B343: ЭХЗ | C343: Материалы по нормам | D343: 38 | E343: МАСЛО ИНДУСТРИАЛЬНОЕ И-20А | F343: Т | G343: 0.00370737 | H343: 11856000 | I343: 43954.579 | J343: 124
A344: ЛРС № 1-2 | B344: ЭХЗ | C344: Материалы по нормам | D344: 39 | E344: СМАЗКА СОЛИДОЛ ЖИРОВОЙ "Ж" | F344: Т | G344: 0.00187285 | H344: 7500000 | I344: 14046.375 | J344: 125
... A500: ЛРС № 1-2 | B500: ЭХЗ | C500: Оборудование | D500: 9 | E500: КОНТРОЛЬНО-ИЗМЕРИТЕЛЬНЫЙ ПУНКТ СКИП-2-6-4-2,0-УХЛ1 | F500: ШТ | G500: 1 | H500: 5739740 | I500: 5739740 | J500: 287
A501: ЛРС № 1-3 | B501: Внешнее электроснабжение 6 кВ средств УКЗ | C501: Затраты труда | D501: 1 | E501: ЗАТРАТЫ ТРУДА РАБОЧИХ-СТРОИТЕЛЕЙ | F501: ЧЕЛ.-Ч | G501: 545.22 | H501: 25287.349 | J501: 19 | K501: цена из строки «Итого по трудовым ресурсам»
A502: ЛРС № 1-3 | B502: Внешнее электроснабжение 6 кВ средств УКЗ | C502: Затраты труда | D502: 2 | E502: ЗАТРАТЫ ТРУДА МАШИНИСТОВ | F502: ЧЕЛ.-Ч | G502: 113.1032 | J502: 20 | K502: оплата машинистов учтена в стоимости маш-ч
A503: ЛРС № 1-3 | B503: Внешнее электроснабжение 6 кВ средств УКЗ | C503: Машины и механизмы | D503: 1 | E503: АВТОГИДРОПОДЪЕМНИКИ ВЫСОТОЙ ПОДЪЕМА 12 М | F503: МАШ.-Ч | G503: 4.02 | H503: 118630 | I503: 476892.6 | J503: 24
A504: ЛРС № 1-3 | B504: Внешнее электроснабжение 6 кВ средств УКЗ | C504: Машины и механизмы | D504: 2 | E504: АГРЕГАТЫ СВАРОЧНЫЕ ПЕРЕДВИЖНЫЕ С НОМИНАЛЬНЫМ СВАРОЧНЫМ ТОКОМ 250-400 А С ДИЗЕЛЬНЫМ ДВИГАТЕЛЕМ | F504: МАШ.-Ч | G504: 13.8 | H504: 111320 | I504: 1536216 | J504: 25
A505: ЛРС № 1-3 | B505: Внешнее электроснабжение 6 кВ средств УКЗ | C505: Машины и механизмы | D505: 3 | E505: ВЫШКИ ТЕЛЕСКОПИЧЕСКИЕ 25 М | F505: МАШ.-Ч | G505: 0.001 | H505: 142421 | I505: 142.421 | J505: 26
A506: ЛРС № 1-3 | B506: Внешнее электроснабжение 6 кВ средств УКЗ | C506: Машины и механизмы | D506: 4 | E506: ДРЕЛИ ЭЛЕКТРИЧЕСКИЕ | F506: МАШ.-Ч | G506: 0.128 | H506: 15000 | I506: 1920 | J506: 27
A507: ЛРС № 1-3 | B507: Внешнее электроснабжение 6 кВ средств УКЗ | C507: Машины и механизмы | D507: 5 | E507: КОМПРЕССОРЫ ПЕРЕДВИЖНЫЕ С ДВИГАТЕЛЕМ ВНУТРЕННЕГО СГОРАНИЯ ДАВЛЕНИЕМ ДО 686 КПА (7 АТМ.) 5 М3/МИН | F507: МАШ.-Ч | G507: 12.2 | H507: 349182.47 | I507: 4260026.1 | J507: 28
A508: ЛРС № 1-3 | B508: Внешнее электроснабжение 6 кВ средств УКЗ | C508: Машины и механизмы | D508: 6 | E508: КРАНЫ НА АВТОМОБИЛЬНОМ ХОДУ ПРИ РАБОТЕ НА МОНТАЖЕ ТЕХНОЛОГИЧЕСКОГО ОБОРУДОВАНИЯ 10 Т | F508: МАШ.-Ч | G508: 13.5506 | H508: 252064 | I508: 3415618.4 | J508: 29
A509: ЛРС № 1-3 | B509: Внешнее электроснабжение 6 кВ средств УКЗ | C509: Машины и механизмы | D509: 7 | E509: ЛЕБЕДКИ ЭЛЕКТРИЧЕСКИЕ, ТЯГОВЫМ УСИЛИЕМ 156,96 (16) КН (Т) | F509: МАШ.-Ч | G509: 33.6 | H509: 33744 | I509: 1133798.4 | J509: 30
A510: ЛРС № 1-3 | B510: Внешнее электроснабжение 6 кВ средств УКЗ | C510: Машины и механизмы | D510: 8 | E510: МАШИНЫ БУРИЛЬНО-КРАНОВЫЕ НА АВТОМОБИЛЕ ГЛУБИНОЙ БУРЕНИЯ 3,5 М | F510: МАШ.-Ч | G510: 18.72 | H510: 197868 | I510: 3704089 | J510: 31
A511: ЛРС № 1-3 | B511: Внешнее электроснабжение 6 кВ средств УКЗ | C511: Машины и механизмы | D511: 9 | E511: ТРАКТОРЫ НА ПНЕВМОКОЛЕСНОМ ХОДУ ПРИ РАБОТЕ НА ДРУГИХ ВИДАХ СТРОИТЕЛЬСТВА (КРОМЕ ВОДОХОЗЯЙСТВЕННОГО) 59 (80) КВТ (Л.С.) | F511: МАШ.-Ч | G511: 7.83 | H511: 155385 | I511: 1216664.6 | J511: 32
A512: ЛРС № 1-3 | B512: Внешнее электроснабжение 6 кВ средств УКЗ | C512: Машины и механизмы | D512: 10 | E512: УСТАНОВКИ ДЛЯ СВАРКИ РУЧНОЙ ДУГОВОЙ (ПОСТОЯННОГО ТОКА) | F512: МАШ.-Ч | G512: 16.8 | H512: 6658 | I512: 111854.4 | J512: 33
A513: ЛРС № 1-3 | B513: Внешнее электроснабжение 6 кВ средств УКЗ | C513: Машины и механизмы | D513: 11 | E513: АВТОМОБИЛИ БОРТОВЫЕ ГРУЗОПОДЪЕМНОСТЬЮ ДО 5 Т | F513: МАШ.-Ч | G513: 9.97 | H513: 428434.3 | I513: 4271490 | J513: 34
A514: ЛРС № 1-3 | B514: Внешнее электроснабжение 6 кВ средств УКЗ | C514: Машины и механизмы | D514: 12 | E514: АВТОМОБИЛИ БОРТОВЫЕ ГРУЗОПОДЪЕМНОСТЬЮ ДО 8 Т | F514: МАШ.-Ч | G514: 13.2116 | H514: 495524.27 | I514: 6546668.4 | J514: 35
... A581: ЛРС № 1-3 | B581: Внешнее электроснабжение 6 кВ средств УКЗ | C581: Оборудование | D581: 1 | E581: СЧЕТЧИК ЭЛЕКТРИЧЕСКОЙ ЭНЕРГИИ 1-Х ФАЗНЫЙ С МАРКА ПРИБОРА УЧЕТА ЭЛЕКТРОЭНЕРГИИ ОПРЕДЕЛЯЕТСЯ ПО СОГЛАСОВАНИЮ С КОМПАНИЕЙ ПО ЭЛЕКТРОСНАБЖЕНИЮ | F581: ШТ | G581: 1 | H581: 1100000 | I581: 1100000 | J581: 111
A582: ЛРС № 1-4 | B582: АС | C582: Затраты труда | D582: 1 | E582: ЗАТРАТЫ ТРУДА РАБОЧИХ-СТРОИТЕЛЕЙ | F582: ЧЕЛ.-Ч | G582: 17614.636 | H582: 25287.349 | J582: 19 | K582: цена из строки «Итого по трудовым ресурсам»
...

Sheet Проверка
A1: ПРОВЕРКА ПОЛНОТЫ ПЕРЕНОСА
A2: Сумма по строкам листа «Все ресурсы» сравнивается с итогом раздела в исходной ЛРС.
A4: ЛРС | B4: Раздел | C4: Итог в исходной ЛРС, сум | D4: Сумма перенесённых строк, сум | E4: Расхождение, сум
A5: ЛРС № 1-1 | B5: Машины и механизмы | C5: 3.5422662e+10 | D5: =SUMIFS('Все ресурсы'!$I$5:$I$706,'Все ресурсы'!$A$5:$A$706,A5,'Все ресурсы'!$C$5:$C$706,B5) -> 3.5422662e+10 | E5: =ROUND(D5-C5,0) -> 0
A6: ЛРС № 1-1 | B6: Материалы по нормам | C6: 9.567009e+09 | D6: =SUMIFS('Все ресурсы'!$I$5:$I$706,'Все ресурсы'!$A$5:$A$706,A6,'Все ресурсы'!$C$5:$C$706,B6) -> 9.567009e+09 | E6: =ROUND(D6-C6,0) -> 0
A7: ЛРС № 1-1 | B7: Ресурсы по проекту | C7: 6.9432399e+10 | D7: =SUMIFS('Все ресурсы'!$I$5:$I$706,'Все ресурсы'!$A$5:$A$706,A7,'Все ресурсы'!$C$5:$C$706,B7) -> 6.9432399e+10 | E7: =ROUND(D7-C7,0) -> 0
A8: ЛРС № 1-1 | B8: Оборудование | C8: 4.5573125e+09 | D8: =SUMIFS('Все ресурсы'!$I$5:$I$706,'Все ресурсы'!$A$5:$A$706,A8,'Все ресурсы'!$C$5:$C$706,B8) -> 4.5573125e+09 | E8: =ROUND(D8-C8,0) -> 0
A9: ЛРС № 1-2 | B9: Машины и механизмы | C9: 1.4646239e+08 | D9: =SUMIFS('Все ресурсы'!$I$5:$I$706,'Все ресурсы'!$A$5:$A$706,A9,'Все ресурсы'!$C$5:$C$706,B9) -> 1.4646239e+08 | E9: =ROUND(D9-C9,0) -> 0
A10: ЛРС № 1-2 | B10: Материалы по нормам | C10: 4.2914583e+08 | D10: =SUMIFS('Все ресурсы'!$I$5:$I$706,'Все ресурсы'!$A$5:$A$706,A10,'Все ресурсы'!$C$5:$C$706,B10) -> 4.2914583e+08 | E10: =ROUND(D10-C10,0) -> 0
A11: ЛРС № 1-2 | B11: Ресурсы по проекту | C11: 1.0240274e+08 | D11: =SUMIFS('Все ресурсы'!$I$5:$I$706,'Все ресурсы'!$A$5:$A$706,A11,'Все ресурсы'!$C$5:$C$706,B11) -> 1.0240274e+08 | E11: =ROUND(D11-C11,0) -> 0
A12: ЛРС № 1-2 | B12: Оборудование | C12: 421753760 | D12: =SUMIFS('Все ресурсы'!$I$5:$I$706,'Все ресурсы'!$A$5:$A$706,A12,'Все ресурсы'!$C$5:$C$706,B12) -> 421753760 | E12: =ROUND(D12-C12,0) -> 0
A13: ЛРС № 1-3 | B13: Машины и механизмы | C13: 26725255 | D13: =SUMIFS('Все ресурсы'!$I$5:$I$706,'Все ресурсы'!$A$5:$A$706,A13,'Все ресурсы'!$C$5:$C$706,B13) -> 26725255 | E13: =ROUND(D13-C13,0) -> 0
A14: ЛРС № 1-3 | B14: Материалы по нормам | C14: 19100870 | D14: =SUMIFS('Все ресурсы'!$I$5:$I$706,'Все ресурсы'!$A$5:$A$706,A14,'Все ресурсы'!$C$5:$C$706,B14) -> 19100870 | E14: =ROUND(D14-C14,0) -> 0
A15: ЛРС № 1-3 | B15: Ресурсы по проекту | C15: 1.9296867e+08 | D15: =SUMIFS('Все ресурсы'!$I$5:$I$706,'Все ресурсы'!$A$5:$A$706,A15,'Все ресурсы'!$C$5:$C$706,B15) -> 1.9296867e+08 | E15: =ROUND(D15-C15,0) -> 0
A16: ЛРС № 1-3 | B16: Оборудование | C16: 1100000 | D16: =SUMIFS('Все ресурсы'!$I$5:$I$706,'Все ресурсы'!$A$5:$A$706,A16,'Все ресурсы'!$C$5:$C$706,B16) -> 1100000 | E16: =ROUND(D16-C16,0) -> 0
... A19: ЛРС № 1-4 | B19: Ресурсы по проекту | C19: 2.3620883e+09 | D19: =SUMIFS('Все ресурсы'!$I$5:$I$706,'Все ресурсы'!$A$5:$A$706,A19,'Все ресурсы'!$C$5:$C$706,B19) -> 2.3620883e+09 | E19: =ROUND(D19-C19,0) -> 0
A21: Затраты труда: цена рабочих взята из строки «Итого по трудовым ресурсам» каждой ЛРС (25 287,35 сум/чел-ч); затраты труда машинистов учтены в стоимости маш-ч.
